graphrag_sdk/__init__.py
graphrag_sdk/client.py
graphrag_sdk/exceptions.py
graphrag_sdk/utils.py
graphrag_sdk_td-0.1.0.dist-info/METADATA
graphrag_sdk_td-0.1.0.dist-info/WHEEL
graphrag_sdk_td-0.1.0.dist-info/top_level.txt
graphrag_sdk_td-0.1.0.dist-info/RECORD
