Metadata-Version: 2.4
Name: graphrag-sdk-td
Version: 0.1.0
Summary: Python SDK cho GraphRAG (chat + upload data)
Author: tungdao
Requires-Dist: requests
